{
  "id": "99f507c2-ebfc-4431-badb-e9a2596407eb",
  "enqueuedAt": 1775206669946,
  "channel": "feishu",
  "to": "heartbeat",
  "payloads": [
    {
      "text": "Architect 任务已成功发送（HTTP 200 ✅）。\n\n## 📊 当前进度\n\n**阶段 3.5 审查结论：REVISE → 已派发修改任务给 Architect**\n\n| 步骤 | 状态 |\n|------|------|\n| Reviewer 框架审查 | ✅ 完成（REVISE） |\n| 读取审查报告 | ✅ |\n| 创建 outline/v2/ 目录 | ✅ |\n| 发送修改任务给 Architect | ✅ HTTP 200 |\n| 等待 Architect 完成 v2 | ⏳ 进行中 |\n\n## 🔧 Architect 修改要点\n\n1. **删除 III. Problem Formulation**，内容合并至 Proposed Method A 节，章节总数降至 6（对齐黄金标准）\n2. **Introduction** 从 ~1500 词压缩至 **850 词**\n3. **Related Work** 从 ~1000 词压缩至 **800 词**\n4. **Proposed Method** 整合后压缩至 **2400 词**\n5. **Experiments** 从 2200 词扩充至 **3200 词**（加强 ablation/讨论）\n6. **Conclusion** 从 400 词压缩至 **250 词**\n7. 总字数目标保持 **9000 词**\n\n等待 Architect 回报完成后，将进行第二轮阶段 3.5 审查（最多 3 轮）。"
    }
  ],
  "threadId": null,
  "mirror": {
    "sessionKey": "agent:main:main",
    "agentId": "main",
    "text": "Architect 任务已成功发送（HTTP 200 ✅）。\n\n## 📊 当前进度\n\n**阶段 3.5 审查结论：REVISE → 已派发修改任务给 Architect**\n\n| 步骤 | 状态 |\n|------|------|\n| Reviewer 框架审查 | ✅ 完成（REVISE） |\n| 读取审查报告 | ✅ |\n| 创建 outline/v2/ 目录 | ✅ |\n| 发送修改任务给 Architect | ✅ HTTP 200 |\n| 等待 Architect 完成 v2 | ⏳ 进行中 |\n\n## 🔧 Architect 修改要点\n\n1. **删除 III. Problem Formulation**，内容合并至 Proposed Method A 节，章节总数降至 6（对齐黄金标准）\n2. **Introduction** 从 ~1500 词压缩至 **850 词**\n3. **Related Work** 从 ~1000 词压缩至 **800 词**\n4. **Proposed Method** 整合后压缩至 **2400 词**\n5. **Experiments** 从 2200 词扩充至 **3200 词**（加强 ablation/讨论）\n6. **Conclusion** 从 400 词压缩至 **250 词**\n7. 总字数目标保持 **9000 词**\n\n等待 Architect 回报完成后，将进行第二轮阶段 3.5 审查（最多 3 轮）。"
  },
  "retryCount": 3,
  "lastAttemptAt": 1775265308161,
  "lastError": "Request failed with status code 400"
}