{
  "id": "0f180f38-d830-401b-b5c6-9dd22abbf4b1",
  "enqueuedAt": 1774774457697,
  "channel": "feishu",
  "to": "heartbeat",
  "payloads": [
    {
      "text": "Reviewer R3 逻辑检查的 11 个问题已全部修复，生成 final/v12：\n\n- Table 2：样本数、采样率、转速全部与正文统一（CWRU 3500 总/2500+1000，SEU 4000 总/2400+1600，5.12kHz，1200-1800rpm）\n- Table 3：学习率→1e-3，weight decay→1e-4，epochs→200，latent/signal/semantic dim→256，新增 BERT raw 1024-d 行\n- Table 4-5：WDCNN 监督基线取消加粗，灰底+脚注标注为 supervised upper bound\n- Table 1：移除 Target Attribute Vector 列，替换为 BERT-large→1024-d→FFN→256-d 语义编码流程\n\n编译通过，13 页，0 错误，0 undefined refs。接下来发给 Reviewer 做最终确认审查。"
    }
  ],
  "threadId": null,
  "mirror": {
    "sessionKey": "agent:main:main",
    "agentId": "main",
    "text": "Reviewer R3 逻辑检查的 11 个问题已全部修复，生成 final/v12：\n\n- Table 2：样本数、采样率、转速全部与正文统一（CWRU 3500 总/2500+1000，SEU 4000 总/2400+1600，5.12kHz，1200-1800rpm）\n- Table 3：学习率→1e-3，weight decay→1e-4，epochs→200，latent/signal/semantic dim→256，新增 BERT raw 1024-d 行\n- Table 4-5：WDCNN 监督基线取消加粗，灰底+脚注标注为 supervised upper bound\n- Table 1：移除 Target Attribute Vector 列，替换为 BERT-large→1024-d→FFN→256-d 语义编码流程\n\n编译通过，13 页，0 错误，0 undefined refs。接下来发给 Reviewer 做最终确认审查。"
  },
  "retryCount": 5,
  "lastAttemptAt": 1775130248432,
  "lastError": "Request failed with status code 400"
}